<?xml version="1.0" encoding="UTF-8"?>
<players>
  <player>
    <id>DBPedia_Udinese_Calcio38328_Cyril_Théréau32248+JokeCampOthers_Udinese1330_Cyril_Théréau1280+Kaggle_Udinese3011_Cyril_Thereau2801+Transfermarkt_Udinese_Calcio129079_Cyril_Théréau122093</id>
    <fullName>Cyril Théréau</fullName>
    <birthDate>1983-04-24</birthDate>
    <birthplace>Privas</birthplace>
    <nationality>FRA</nationality>
    <height>189</height>
    <weight>78</weight>
    <shirtNumberOfClub>77</shirtNumberOfClub>
    <position>FW</position>
    <preferredFoot>left</preferredFoot>
    <isInNationalTeam>false</isInNationalTeam>
    <clubMembershipValidAsOf>2016-05-01</clubMembershipValidAsOf>
  </player>
  <player>
    <id>DBPedia_CA_Osasuna19758_Luís_Martins16774+JokeCampOthers_Granada4043_Luís_Martins3894+Kaggle_Gil_Vicente_FC1320_Luis_Martins1230+Transfermarkt_CA_Osasuna211999_Luís_Martins198334</id>
    <fullName>Luís Martins</fullName>
    <birthDate>1992-06-10</birthDate>
    <nationality>PRT</nationality>
    <height>177</height>
    <weight>67</weight>
    <shirtNumberOfClub>3</shirtNumberOfClub>
    <position>DF</position>
    <preferredFoot>right</preferredFoot>
    <isInNationalTeam>false</isInNationalTeam>
    <clubMembershipValidAsOf>2016-05-01</clubMembershipValidAsOf>
  </player>
  <player>
    <id>DBPedia_Atlético_Madrid11951_Antoine_Griezmann10076+Euro2016_Atlético_Madrid216_Antoine_Griezmann166+JokeCampOthers_Atletico890_Antoine_Griezmann856+Kaggle_Atlético_Madrid3167_Antoine_Griezmann2943+Transfermarkt_Atlético_Madrid2773_Antoine_Griezmann2641</id>
    <fullName>Antoine Griezmann</fullName>
    <birthDate>1991-03-21</birthDate>
    <birthplace>Mâcon</birthplace>
    <nationality>FRA</nationality>
    <height>175</height>
    <weight>67</weight>
    <shirtNumberOfClub>7</shirtNumberOfClub>
    <position>FW</position>
    <caps>26</caps>
    <preferredFoot>left</preferredFoot>
    <isInNationalTeam>true</isInNationalTeam>
    <clubMembershipValidAsOf>2016-06-10</clubMembershipValidAsOf>
  </player>
</players>